lmms_lab_meter/__init__.py
lmms_lab_meter/__main__.py
lmms_lab_meter/api/client.py
lmms_lab_meter/protocols/__init__.py
lmms_lab_meter/protocols/customer.py
lmms_lab_meter/protocols/events.py
lmms_lab_meter/protocols/features.py
lmms_lab_meter/protocols/meter.py
lmms_lab_meter/protocols/plans.py
lmms_lab_meter/protocols/subscriptions.py
lmms_lab_meter-0.1.0.dist-info/METADATA
lmms_lab_meter-0.1.0.dist-info/WHEEL
lmms_lab_meter-0.1.0.dist-info/top_level.txt
lmms_lab_meter-0.1.0.dist-info/RECORD
