Metadata-Version: 2.4
Name: lmms-lab-meter
Version: 0.1.0
Summary: A python metering tool using open meter
Author-email: Kaichen Zhang <kaichenzhang358@outlook.com>
License: MIT
Project-URL: Homepage, https://xxx.github.io
Project-URL: Repository, https://github.com/xxx/yyy
Classifier: Programming Language :: Python :: 3
Classifier: License :: OSI Approved :: MIT License
Classifier: Operating System :: OS Independent
Requires-Python: >=3.8
Requires-Dist: pydantic
Provides-Extra: opt
